cdk_soca/__init__.py
cdk_soca/py.typed
cdk_soca/_jsii/__init__.py
cdk_soca/_jsii/cdk-soca@0.2.98.jsii.tgz
cdk_soca-0.2.98.dist-info/LICENSE
cdk_soca-0.2.98.dist-info/METADATA
cdk_soca-0.2.98.dist-info/WHEEL
cdk_soca-0.2.98.dist-info/top_level.txt
cdk_soca-0.2.98.dist-info/RECORD
