Metadata-Version: 2.1
Name: cdk-soca
Version: 0.2.98
Summary: cdk-soca is an AWS CDK construct library that allows you to create the Scale-Out Computing on AWS with AWS CDK in TypeScript or Python
Home-page: https://github.com/pahud/cdk-soca.git
Author: Pahud Hsieh<pahudnet@gmail.com>
License: Apache-2.0
Project-URL: Source, https://github.com/pahud/cdk-soca.git
Platform: UNKNOWN
Classifier: Intended Audience :: Developers
Classifier: Operating System :: OS Independent
Classifier: Programming Language :: JavaScript
Classifier: Programming Language :: Python :: 3 :: Only
Classifier: Programming Language :: Python :: 3.6
Classifier: Programming Language :: Python :: 3.7
Classifier: Programming Language :: Python :: 3.8
Classifier: Programming Language :: Python :: 3.9
Classifier: Typing :: Typed
Classifier: Development Status :: 4 - Beta
Classifier: License :: OSI Approved
Requires-Python: >=3.6
Requires-Dist: aws-cdk.aws-ec2 (<2.0.0,>=1.96.0)
Requires-Dist: aws-cdk.aws-efs (<2.0.0,>=1.96.0)
Requires-Dist: aws-cdk.aws-elasticsearch (<2.0.0,>=1.96.0)
Requires-Dist: aws-cdk.aws-iam (<2.0.0,>=1.96.0)
Requires-Dist: aws-cdk.aws-s3 (<2.0.0,>=1.96.0)
Requires-Dist: aws-cdk.core (<2.0.0,>=1.96.0)
Requires-Dist: constructs (<4.0.0,>=3.2.27)
Requires-Dist: jsii (<2.0.0,>=1.32.0)
Requires-Dist: publication (>=0.0.3)
